scaleway_tink/__init__.py
scaleway_tink/integration/__init__.py
scaleway_tink/integration/scwkms/__init__.py
scaleway_tink/integration/scwkms/client.py
scaleway_tink/integration/scwkms/test_client.py
scaleway_tink-0.2.2.dist-info/LICENSE
scaleway_tink-0.2.2.dist-info/METADATA
scaleway_tink-0.2.2.dist-info/WHEEL
scaleway_tink-0.2.2.dist-info/RECORD
