Metadata-Version: 2.1
Name: scaleway-tink
Version: 0.2.2
Summary: Extension to Tink Python that provides Scaleway's Key Manager integration
Home-page: https://github.com/scaleway/tink-py-scwkms
License: Apache-2.0
Author: Scaleway
Author-email: opensource@scaleway.com
Requires-Python: >=3.8,<4.0
Classifier: License :: OSI Approved :: Apache Software License
Classifier: Programming Language :: Python :: 3
Classifier: Programming Language :: Python :: 3.8
Classifier: Programming Language :: Python :: 3.9
Classifier: Programming Language :: Python :: 3.10
Classifier: Programming Language :: Python :: 3.11
Classifier: Programming Language :: Python :: 3.12
Requires-Dist: scaleway (>=2.3.1,<3.0.0)
Requires-Dist: setuptools (>=70.0.0,<71.0.0)
Requires-Dist: tink (>=1.10.0,<2.0.0)
Project-URL: Documentation, https://github.com/scaleway/tink-py-scwkms
Project-URL: Repository, https://github.com/scaleway/tink-py-scwkms
